hmtnote/__init__.py
hmtnote/classes.py
hmtnote/cli.py
hmtnote/hmtnote.py
hmtnote-0.7.2.dist-info/AUTHORS.rst
hmtnote-0.7.2.dist-info/LICENSE
hmtnote-0.7.2.dist-info/METADATA
hmtnote-0.7.2.dist-info/WHEEL
hmtnote-0.7.2.dist-info/entry_points.txt
hmtnote-0.7.2.dist-info/top_level.txt
hmtnote-0.7.2.dist-info/RECORD
