Metadata-Version: 2.1
Name: hmtnote
Version: 0.7.2
Summary: Human mitochondrial variants annotation using HmtVar.
Home-page: https://github.com/robertopreste/hmtnote
Author: Roberto Preste
Author-email: robertopreste@gmail.com
License: MIT license
Keywords: hmtnote
Platform: UNKNOWN
Classifier: Development Status :: 4 - Beta
Classifier: Intended Audience :: Developers
Classifier: License :: OSI Approved :: MIT License
Classifier: Natural Language :: English
Classifier: Programming Language :: Python :: 3
Classifier: Programming Language :: Python :: 3.6
Classifier: Programming Language :: Python :: 3.7
Requires-Dist: Click (==7.0)
Requires-Dist: requests (==2.22.0)
Requires-Dist: numpy (==1.16.4)
Requires-Dist: pandas (==0.24.2)
Requires-Dist: aiohttp (==3.5.4)
Requires-Dist: aiofiles (==0.4.0)
Requires-Dist: vcfpy2 (==0.1.2)
Requires-Dist: scikit-allel (==1.2.1)
